odoo10_addon_account_financial_report_horizontal-10.0.1.0.0-py2.7-nspkg.pth
odoo/addons/account_financial_report_horizontal/README.rst
odoo/addons/account_financial_report_horizontal/__init__.py
odoo/addons/account_financial_report_horizontal/__manifest__.py
odoo/addons/account_financial_report_horizontal/data/ir_actions_report_xml.xml
odoo/addons/account_financial_report_horizontal/data/report_paperformat.xml
odoo/addons/account_financial_report_horizontal/i18n/ca.po
odoo/addons/account_financial_report_horizontal/i18n/de.po
odoo/addons/account_financial_report_horizontal/i18n/es.po
odoo/addons/account_financial_report_horizontal/i18n/fr.po
odoo/addons/account_financial_report_horizontal/i18n/pt.po
odoo/addons/account_financial_report_horizontal/models/__init__.py
odoo/addons/account_financial_report_horizontal/models/account_financial_report.py
odoo/addons/account_financial_report_horizontal/report/__init__.py
odoo/addons/account_financial_report_horizontal/report/report_financial.py
odoo/addons/account_financial_report_horizontal/report/report_financial.xml
odoo/addons/account_financial_report_horizontal/static/description/icon.png
odoo/addons/account_financial_report_horizontal/tests/__init__.py
odoo/addons/account_financial_report_horizontal/tests/test_account_financial_report_horizontal.py
odoo10_addon_account_financial_report_horizontal-10.0.1.0.0.dist-info/DESCRIPTION.rst
odoo10_addon_account_financial_report_horizontal-10.0.1.0.0.dist-info/METADATA
odoo10_addon_account_financial_report_horizontal-10.0.1.0.0.dist-info/RECORD
odoo10_addon_account_financial_report_horizontal-10.0.1.0.0.dist-info/WHEEL
odoo10_addon_account_financial_report_horizontal-10.0.1.0.0.dist-info/metadata.json
odoo10_addon_account_financial_report_horizontal-10.0.1.0.0.dist-info/namespace_packages.txt
odoo10_addon_account_financial_report_horizontal-10.0.1.0.0.dist-info/top_level.txt
